cellpose_plus/__init__.py
cellpose_plus/__main__.py
cellpose_plus/cell_brightness.py
cellpose_plus/cli.py
cellpose_plus/core.py
cellpose_plus/denoise.py
cellpose_plus/dynamics.py
cellpose_plus/export.py
cellpose_plus/io.py
cellpose_plus/metrics.py
cellpose_plus/models.py
cellpose_plus/plot.py
cellpose_plus/resnet_torch.py
cellpose_plus/segformer.py
cellpose_plus/test_mkl.py
cellpose_plus/train.py
cellpose_plus/transforms.py
cellpose_plus/utils.py
cellpose_plus/version.py
cellpose_plus/contrib/distributed_segmentation.py
cellpose_plus/gui/features.py
cellpose_plus/gui/gui.py
cellpose_plus/gui/gui3d.py
cellpose_plus/gui/guihelpwindowtext.html
cellpose_plus/gui/guiparts.py
cellpose_plus/gui/guitrainhelpwindowtext.html
cellpose_plus/gui/io.py
cellpose_plus/gui/make_train.py
cellpose_plus/gui/menus.py
cellpose_plus/gui/symmetry.py
cellpose_plus/logo/cellpose.ico
cellpose_plus/logo/logo.png
cellpose_plus/resources/4-2-20x_Image020_Properties.xml
cellpose_plus/resources/4-2-20x_Image020_ch00.tif
cellpose_plus/resources/DejaVuSans.ttf
cellpose_plus/resources/primary.png
cellpose_plus/resources/secondary.png
cellpose_plus-0.0.19.dist-info/LICENSE
cellpose_plus-0.0.19.dist-info/METADATA
cellpose_plus-0.0.19.dist-info/WHEEL
cellpose_plus-0.0.19.dist-info/entry_points.txt
cellpose_plus-0.0.19.dist-info/top_level.txt
cellpose_plus-0.0.19.dist-info/RECORD
