Metadata-Version: 2.1
Name: cellpose_plus
Version: 0.0.19
Summary: cell segmentation framework based on cellpose
Home-page: https://github.com/ITMO-MMRM-lab/cellpose
Author: Israel Huaman
Author-email: ihuaman@itmo.ru
License: BSD
Classifier: Programming Language :: Python :: 3
Classifier: License :: OSI Approved :: BSD License
Classifier: Operating System :: OS Independent
License-File: LICENSE
Requires-Dist: numpy<2.1,>=1.20.0
Requires-Dist: pandas
Requires-Dist: matplotlib
Requires-Dist: scipy
Requires-Dist: natsort
Requires-Dist: tifffile
Requires-Dist: tqdm
Requires-Dist: numba>=0.53.0
Requires-Dist: llvmlite
Requires-Dist: opencv-python
Requires-Dist: fastremap
Requires-Dist: Cython
Requires-Dist: imagecodecs
Requires-Dist: roifile
Provides-Extra: all
Requires-Dist: pyqtgraph>=0.11.0rc0; extra == "all"
Requires-Dist: qtpy; extra == "all"
Requires-Dist: superqt; extra == "all"
Requires-Dist: diplib; extra == "all"
Requires-Dist: Pillow; extra == "all"
Requires-Dist: pyqt5; extra == "all"
Requires-Dist: pyqt5.sip; extra == "all"
Requires-Dist: dask; extra == "all"
Requires-Dist: distributed; extra == "all"
Requires-Dist: dask-image; extra == "all"
Requires-Dist: pyyaml; extra == "all"
Requires-Dist: zarr; extra == "all"
Requires-Dist: dask-jobqueue; extra == "all"
Requires-Dist: bokeh; extra == "all"
Requires-Dist: nd2; extra == "all"
Requires-Dist: pynrrd; extra == "all"
Requires-Dist: bioimageio.core; extra == "all"
Provides-Extra: bioimageio
Requires-Dist: bioimageio.core; extra == "bioimageio"
Provides-Extra: distributed
Requires-Dist: dask; extra == "distributed"
Requires-Dist: distributed; extra == "distributed"
Requires-Dist: dask-image; extra == "distributed"
Requires-Dist: pyyaml; extra == "distributed"
Requires-Dist: zarr; extra == "distributed"
Requires-Dist: dask-jobqueue; extra == "distributed"
Requires-Dist: bokeh; extra == "distributed"
Provides-Extra: docs
Requires-Dist: sphinx>=3.0; extra == "docs"
Requires-Dist: sphinxcontrib-apidoc; extra == "docs"
Requires-Dist: sphinx-rtd-theme; extra == "docs"
Requires-Dist: sphinx-argparse; extra == "docs"
Provides-Extra: gui
Requires-Dist: pyqtgraph>=0.11.0rc0; extra == "gui"
Requires-Dist: qtpy; extra == "gui"
Requires-Dist: superqt; extra == "gui"
Requires-Dist: diplib; extra == "gui"
Requires-Dist: Pillow; extra == "gui"
Requires-Dist: pyqt5; extra == "gui"
Requires-Dist: pyqt5.sip; extra == "gui"
